mcp_llm_inferencer/__init__.py
mcp_llm_inferencer/main.py
mcp_llm_inferencer-0.1.0.dist-info/METADATA
mcp_llm_inferencer-0.1.0.dist-info/WHEEL
mcp_llm_inferencer-0.1.0.dist-info/top_level.txt
mcp_llm_inferencer-0.1.0.dist-info/RECORD
